fgspectra/__init__.py
fgspectra/_version.py
fgspectra/cross.py
fgspectra/frequency.py
fgspectra/model.py
fgspectra/power.py
fgspectra/data/cl_cib_Choi2020.dat
fgspectra/data/cl_ksz_bat.dat
fgspectra/data/cl_ksz_bat_full.dat
fgspectra/data/cl_sz_x_cib.dat
fgspectra/data/cl_tsz_150_bat.dat
fgspectra-1.4.1.dist-info/licenses/LICENSE
fgspectra-1.4.1.dist-info/METADATA
fgspectra-1.4.1.dist-info/WHEEL
fgspectra-1.4.1.dist-info/top_level.txt
fgspectra-1.4.1.dist-info/RECORD
