Metadata-Version: 2.4
Name: fgspectra
Version: 1.4.1
Summary: Foreground SED and power spectrum library for building cross frequency power spectrum models
Author-email: Zack Li <xzackli@gmail.com>, Benjamin Beringue <beringueb@gmail.com>
Project-URL: Homepage, https://github.com/simonsobs/fgspectra
Keywords: astrophysics,foregrounds,cmb
Classifier: License :: OSI Approved :: MIT License
Classifier: Programming Language :: Python
Classifier: Programming Language :: Python :: 3
Requires-Python: >=3.9
License-File: LICENSE
Requires-Dist: scipy
Requires-Dist: pyyaml
Provides-Extra: dev
Requires-Dist: black; extra == "dev"
Requires-Dist: bumpver; extra == "dev"
Requires-Dist: isort; extra == "dev"
Requires-Dist: pip-tools; extra == "dev"
Requires-Dist: pytest; extra == "dev"
Dynamic: license-file
